byllm/__init__.py
byllm/config_loader.jac
byllm/lib.jac
byllm/llm.jac
byllm/mtir.jac
byllm/plugin.jac
byllm/plugin_config.jac
byllm/schema.jac
byllm/types.jac
byllm/impl/config_loader.impl.jac
byllm/impl/mtir.impl.jac
byllm/impl/schema.impl.jac
byllm/llm.impl/basellm.impl.jac
byllm/llm.impl/mockllm.impl.jac
byllm/llm.impl/model.impl.jac
byllm/types.impl/media.impl.jac
byllm/types.impl/message.impl.jac
byllm/types.impl/tool.impl.jac
byllm/types.impl/toolcall.impl.jac
byllm-0.4.17.dist-info/METADATA
byllm-0.4.17.dist-info/WHEEL
byllm-0.4.17.dist-info/entry_points.txt
byllm-0.4.17.dist-info/top_level.txt
byllm-0.4.17.dist-info/RECORD
