Metadata-Version: 2.4
Name: byllm
Version: 0.4.17
Summary: byLLM Provides Easy to use APIs for different LLM Providers to be used with Jaseci's Jaclang Programming Language.
Author-email: Jason Mars <jason@mars.ninja>
Maintainer-email: Jason Mars <jason@mars.ninja>
License-Expression: MIT
Keywords: llm,jaclang,jaseci,byLLM
Requires-Python: >=3.11
Requires-Dist: jaclang>=0.9.13
Requires-Dist: litellm<1.80.0,>=1.75.5.post1
Requires-Dist: loguru<0.8.0,>=0.7.2
Requires-Dist: pillow<10.5.0,>=10.4.0
Provides-Extra: dev
Requires-Dist: pytest>=8.3.2; extra == "dev"
Provides-Extra: tools
Requires-Dist: wikipedia; extra == "tools"
Provides-Extra: video
Requires-Dist: opencv-python-headless; extra == "video"
